magicBatch/MAGIC.py
magicBatch/MAGIC_core.py
magicBatch/__init__.py
magicBatch-0.0.data/scripts/MAGIC.py
magicBatch-0.0.dist-info/METADATA
magicBatch-0.0.dist-info/WHEEL
magicBatch-0.0.dist-info/top_level.txt
magicBatch-0.0.dist-info/RECORD
